Workbook

Sheet Read Me
A1: Ravaan Medical Group - Consolidation & FX Translation
A2: Fictional company, generated data (seeded). Reporting currency AED. Actuals Jan-2025 to Sep-2026; budget FY2026.
A4: Group | B4: Ravaan Medical Group Holding Ltd (Dubai head office) owns 8 operating subsidiaries - UAE, KSA, Qatar, Kuwait, Pakistan, Afghanistan, UK, USA - running 18 clinics.
A5: Translation (IAS 21) | B5: Income and expenses at each month's average rate; assets and liabilities at the month-end closing rate; share capital at the historical rate; retained earnings = opening balance at historical rate + profit translated month by month.
A6: Translation reserve (CTA) | B6: The balancing figure: translated net assets - share capital - retained earnings. It sits in equity (other comprehensive income), never in profit.
A7: Eliminations | B7: 1) Head-office management fee (4% of each subsidiary's net revenue): income in the holding company, expense in the subsidiaries - removed on consolidation. 2) Investment in subsidiaries (holding company) against the subsidiaries' share capital.
A8: Pegged currencies | B8: SAR, QAR and USD are pegged to the dollar like the AED, so they create almost no translation difference; KWD follows a basket. PKR, AFN and GBP float - that is where the FX story is.
A9: Constant currency | B9: Organic growth = this year's local-currency results at last year's rates vs last year. FX impact = reported AED - constant-currency AED.
A10: How to read the sheets | B10: FX Rates -> Entity TB (local currency) -> Translation (formulas) -> Eliminations -> Consolidation (sum of entities + eliminations) -> statements.
A11: Source | B11: Data\*.csv generated by gen_data.py; this workbook by build_consolidation.py. The Power BI report reads the same CSVs, so the numbers agree.

Sheet FX Rates
A1: Exchange rates - AED per 1 unit of local currency
A2: Average = mean of opening and closing month-end rate. Budget rate FY2026 = 31-Dec-2025 closing. Historical = rate when share capital was injected.
A4: Month | B4: SAR avg | C4: QAR avg | D4: KWD avg | E4: PKR avg | F4: AFN avg | G4: GBP avg | H4: USD avg | I4: SAR close | J4: QAR close | K4: KWD close | L4: PKR close | M4: AFN close | N4: GBP close | O4: USD close
A5: Dec-24 | B5: 0.97933333 | C5: 1.0089286 | D5: 11.927686 | E5: 0.01324183 | F5: 0.0524841 | G5: 4.613062 | H5: 3.6725 | I5: 0.97933333 | J5: 1.0089286 | K5: 11.929605 | L5: 0.01325605 | M5: 0.05264161 | N5: 4.5873564 | O5: 3.6725
A6: Jan-25 | B6: 0.97933333 | C6: 1.0089286 | D6: 11.929584 | E6: 0.01319127 | F6: 0.05242656 | G6: 4.6328383 | H6: 3.6725 | I6: 0.97933333 | J6: 1.0089286 | K6: 11.929563 | L6: 0.01312649 | M6: 0.0522115 | N6: 4.6783202 | O6: 3.6725
A7: Feb-25 | B7: 0.97933333 | C7: 1.0089286 | D7: 11.927662 | E7: 0.01313429 | F7: 0.05232934 | G7: 4.7035472 | H7: 3.6725 | I7: 0.97933333 | J7: 1.0089286 | K7: 11.92576 | L7: 0.0131421 | M7: 0.05244719 | N7: 4.7287742 | O7: 3.6725
A8: Mar-25 | B8: 0.97933333 | C8: 1.0089286 | D8: 11.918385 | E8: 0.0131418 | F8: 0.05259945 | G8: 4.7768506 | H8: 3.6725 | I8: 0.97933333 | J8: 1.0089286 | K8: 11.91101 | L8: 0.0131415 | M8: 0.05275171 | N8: 4.824927 | O8: 3.6725
A9: Apr-25 | B9: 0.97933333 | C9: 1.0089286 | D9: 11.919831 | E9: 0.01310056 | F9: 0.05283955 | G9: 4.8423175 | H9: 3.6725 | I9: 0.97933333 | J9: 1.0089286 | K9: 11.928652 | L9: 0.01305962 | M9: 0.0529274 | N9: 4.8597079 | O9: 3.6725
A10: May-25 | B10: 0.97933333 | C10: 1.0089286 | D10: 11.934202 | E10: 0.01304629 | F10: 0.05301338 | G10: 4.8989938 | H10: 3.6725 | I10: 0.97933333 | J10: 1.0089286 | K10: 11.939752 | L10: 0.01303295 | M10: 0.05309937 | N10: 4.9382797 | O10: 3.6725
A11: Jun-25 | B11: 0.97933333 | C11: 1.0089286 | D11: 11.92762 | E11: 0.01305819 | F11: 0.05298124 | G11: 4.9647672 | H11: 3.6725 | I11: 0.97933333 | J11: 1.0089286 | K11: 11.915487 | L11: 0.01308344 | M11: 0.0528631 | N11: 4.9912548 | O11: 3.6725
A12: Jul-25 | B12: 0.97933333 | C12: 1.0089286 | D12: 11.927531 | E12: 0.01302489 | F12: 0.05312022 | G12: 4.9759177 | H12: 3.6725 | I12: 0.97933333 | J12: 1.0089286 | K12: 11.939574 | L12: 0.01296635 | M12: 0.05337735 | N12: 4.9605806 | O12: 3.6725
A13: Aug-25 | B13: 0.97933333 | C13: 1.0089286 | D13: 11.945036 | E13: 0.01299334 | F13: 0.05320825 | G13: 4.9820881 | H13: 3.6725 | I13: 0.97933333 | J13: 1.0089286 | K13: 11.950498 | L13: 0.01302033 | M13: 0.05303914 | N13: 5.0035956 | O13: 3.6725
A14: Sep-25 | B14: 0.97933333 | C14: 1.0089286 | D14: 11.939905 | E14: 0.01303221 | F14: 0.05328332 | G14: 4.9728571 | H14: 3.6725 | I14: 0.97933333 | J14: 1.0089286 | K14: 11.929313 | L14: 0.0130441 | M14: 0.05352749 | N14: 4.9421187 | O14: 3.6725
A15: Oct-25 | B15: 0.97933333 | C15: 1.0089286 | D15: 11.929304 | E15: 0.01301958 | F15: 0.05363471 | G15: 4.9466243 | H15: 3.6725 | I15: 0.97933333 | J15: 1.0089286 | K15: 11.929296 | L15: 0.01299506 | M15: 0.05374193 | N15: 4.9511299 | O15: 3.6725
A16: Nov-25 | B16: 0.97933333 | C16: 1.0089286 | D16: 11.932371 | E16: 0.01300025 | F16: 0.05378209 | G16: 4.9424724 | H16: 3.6725 | I16: 0.97933333 | J16: 1.0089286 | K16: 11.935446 | L16: 0.01300545 | M16: 0.05382225 | N16: 4.9338149 | O16: 3.6725
... A29: Dec-26 | B29: 0.97933333 | C29: 1.0089286 | D29: 11.883717 | E29: 0.01098597 | F29: 0.04286474 | G29: 4.4186463 | H29: 3.6725 | I29: 0.97933333 | J29: 1.0089286 | K29: 11.892258 | L29: 0.01097287 | M29: 0.04284802 | N29: 4.4011122 | O29: 3.6725
A31: Budget rate FY2026 | B31: 0.97933333 | C31: 1.0089286 | D31: 11.91848 | E31: 0.01308234 | F31: 0.05338162 | G31: 4.9315551 | H31: 3.6725
A32: Historical (share capital) | B32: 0.97933333 | C32: 1.0089286 | D32: 12.08 | E32: 0.030102459 | F32: 0.041732955 | G32: 4.85 | H32: 3.6725

Sheet Entity TB (LCY)
A1: Entity trial balances in local currency
A2: P&L: Jan-Sep 2026 year to date. Balance sheet: 30 September 2026. Profit sign: income +, costs -.
A4: Account | B4: Name | C4: Statement | D4: UAE (AED) | E4: KSA (SAR) | F4: Qatar (QAR) | G4: Kuwait (KWD) | H4: Pakistan (PKR) | I4: Afghanistan (AFN) | J4: UK (GBP) | K4: USA (USD) | L4: Head office (AED)
A5: 4000 | B5: Consultation revenue | C5: P&L | D5: 39833952 | E5: 27021367 | F5: 13895614 | G5: 1295043 | H5: 294434962 | I5: 12190891 | J5: 5463875 | K5: 10568757 | L5: 0
A6: 4100 | B6: Procedures revenue | C6: P&L | D6: 31579079 | E6: 22346169 | F6: 11446100 | G6: 1022366 | H6: 201871074 | I6: 6913207 | J6: 4224711 | K6: 8398985 | L6: 0
A7: 4200 | B7: Diagnostics revenue | C7: P&L | D7: 8654493 | E7: 5058412 | F7: 2896589 | G7: 278594 | H7: 51972028 | I7: 2624507 | J7: 1190128 | K7: 2286049 | L7: 0
A8: 4300 | B8: Pharmacy revenue | C8: P&L | D8: 7837703 | E8: 5505851 | F8: 2770658 | G8: 255831 | H8: 59376417 | I8: 2209863 | J8: 1079226 | K8: 2136771 | L8: 0
A9: 4900 | B9: Contractual discounts | C9: P&L | D9: -10496596 | E9: -7317274 | F9: -3503736 | G9: -293651 | H9: -41565340 | I9: -1555579 | J9: -1406242 | K9: -8045627 | L9: 0
A10: 5000 | B10: Doctor salaries | C10: P&L | D10: -23291963 | E10: -15814145 | F10: -10178993 | G10: -822335 | H10: -115788554 | I10: -6547693 | J10: -3533741 | K10: -5985084 | L10: 0
A11: 5100 | B11: Nursing & clinical staff | C11: P&L | D11: -6673833 | E11: -4561309 | F11: -2902576 | G11: -235024 | H11: -35227947 | I11: -1843455 | J11: -1005220 | K11: -1760673 | L11: 0
A12: 5200 | B12: Medical consumables | C12: P&L | D12: -6226733 | E12: -4236298 | F12: -2246990 | G12: -204952 | H12: -43158166 | I12: -1710793 | J12: -849553 | K12: -1238908 | L12: 0
A13: 5300 | B13: Pharmacy cost of goods | C13: P&L | D13: -4693615 | E13: -3287316 | F13: -1667143 | G13: -155318 | H13: -37670506 | I13: -1393884 | J13: -641641 | K13: -946301 | L13: 0
A14: 6000 | B14: Rent & facility | C14: P&L | D14: -6303600 | E14: -3786249 | F14: -3032028 | G14: -202035 | H14: -42582818 | I14: -2513221 | J14: -1015291 | K14: -1192117 | L14: 0
A15: 6100 | B15: Admin & front-office staff | C15: P&L | D15: -4422600 | E15: -3162276 | F15: -1997173 | G15: -161982 | H15: -29276053 | I15: -1371790 | J15: -627675 | K15: -1097029 | L15: 0
A16: 6200 | B16: Marketing | C16: P&L | D16: -1676653 | E16: -1173049 | F16: -598674 | G16: -56333 | H16: -12669808 | I16: -487816 | J16: -253055 | K16: -336975 | L16: 0
... A39: 3100 | B39: Retained earnings | C39: BS | D39: 30125158 | E39: 18530130 | F39: 9605635 | G39: 1280302 | H39: -22620891 | I39: 9453641 | J39: -724690 | K39: -1611071 | L39: -6815079

Sheet Translation
A1: Translation to AED - 30 September 2026 (P&L = Jan-Sep 2026)
A2: P&L is translated month by month; the rate shown for P&L lines is the effective YTD rate (AED / LCY). Balance sheet uses closing rate; equity historical; CTA balances.
A4: Account | B4: Name | C4: Rate type | D4: UAE LCY | E4: Rate | F4: UAE AED | G4: KSA LCY | H4: Rate | I4: KSA AED | J4: Qatar LCY | K4: Rate | L4: Qatar AED | M4: Kuwait LCY | N4: Rate | O4: Kuwait AED | P4: Pakistan LCY | Q4: Rate | R4: Pakistan AED | S4: Afghanistan LCY | T4: Rate | U4: Afghanistan AED | V4: UK LCY | W4: Rate | X4: UK AED | Y4: USA LCY | Z4: Rate | AA4: USA AED | AB4: Head office LCY | AC4: Rate | AD4: Head office AED
A5: 4000 | B5: Consultation revenue | C5: Average | D5: ='Entity TB (LCY)'!D5 | E5: 1 | F5: =D5*E5 | G5: ='Entity TB (LCY)'!E5 | H5: 0.97933333 | I5: =G5*H5 | J5: ='Entity TB (LCY)'!F5 | K5: 1.0089286 | L5: =J5*K5 | M5: ='Entity TB (LCY)'!G5 | N5: 11.915835 | O5: =M5*N5 | P5: ='Entity TB (LCY)'!H5 | Q5: 0.012111314 | R5: =P5*Q5 | S5: ='Entity TB (LCY)'!I5 | T5: 0.049243654 | U5: =S5*T5 | V5: ='Entity TB (LCY)'!J5 | W5: 4.6432743 | X5: =V5*W5 | Y5: ='Entity TB (LCY)'!K5 | Z5: 3.6725 | AA5: =Y5*Z5 | AB5: ='Entity TB (LCY)'!L5 | AC5: 1 | AD5: =AB5*AC5
A6: 4100 | B6: Procedures revenue | C6: Average | D6: ='Entity TB (LCY)'!D6 | E6: 1 | F6: =D6*E6 | G6: ='Entity TB (LCY)'!E6 | H6: 0.97933333 | I6: =G6*H6 | J6: ='Entity TB (LCY)'!F6 | K6: 1.0089286 | L6: =J6*K6 | M6: ='Entity TB (LCY)'!G6 | N6: 11.915828 | O6: =M6*N6 | P6: ='Entity TB (LCY)'!H6 | Q6: 0.012110416 | R6: =P6*Q6 | S6: ='Entity TB (LCY)'!I6 | T6: 0.049241708 | U6: =S6*T6 | V6: ='Entity TB (LCY)'!J6 | W6: 4.6424462 | X6: =V6*W6 | Y6: ='Entity TB (LCY)'!K6 | Z6: 3.6725 | AA6: =Y6*Z6 | AB6: ='Entity TB (LCY)'!L6 | AC6: 1 | AD6: =AB6*AC6
A7: 4200 | B7: Diagnostics revenue | C7: Average | D7: ='Entity TB (LCY)'!D7 | E7: 1 | F7: =D7*E7 | G7: ='Entity TB (LCY)'!E7 | H7: 0.97933333 | I7: =G7*H7 | J7: ='Entity TB (LCY)'!F7 | K7: 1.0089286 | L7: =J7*K7 | M7: ='Entity TB (LCY)'!G7 | N7: 11.915832 | O7: =M7*N7 | P7: ='Entity TB (LCY)'!H7 | Q7: 0.012112269 | R7: =P7*Q7 | S7: ='Entity TB (LCY)'!I7 | T7: 0.049242976 | U7: =S7*T7 | V7: ='Entity TB (LCY)'!J7 | W7: 4.6414138 | X7: =V7*W7 | Y7: ='Entity TB (LCY)'!K7 | Z7: 3.6725 | AA7: =Y7*Z7 | AB7: ='Entity TB (LCY)'!L7 | AC7: 1 | AD7: =AB7*AC7
A8: 4300 | B8: Pharmacy revenue | C8: Average | D8: ='Entity TB (LCY)'!D8 | E8: 1 | F8: =D8*E8 | G8: ='Entity TB (LCY)'!E8 | H8: 0.97933333 | I8: =G8*H8 | J8: ='Entity TB (LCY)'!F8 | K8: 1.0089286 | L8: =J8*K8 | M8: ='Entity TB (LCY)'!G8 | N8: 11.915833 | O8: =M8*N8 | P8: ='Entity TB (LCY)'!H8 | Q8: 0.012111171 | R8: =P8*Q8 | S8: ='Entity TB (LCY)'!I8 | T8: 0.049242983 | U8: =S8*T8 | V8: ='Entity TB (LCY)'!J8 | W8: 4.643283 | X8: =V8*W8 | Y8: ='Entity TB (LCY)'!K8 | Z8: 3.6725 | AA8: =Y8*Z8 | AB8: ='Entity TB (LCY)'!L8 | AC8: 1 | AD8: =AB8*AC8
A9: 4900 | B9: Contractual discounts | C9: Average | D9: ='Entity TB (LCY)'!D9 | E9: 1 | F9: =D9*E9 | G9: ='Entity TB (LCY)'!E9 | H9: 0.97933333 | I9: =G9*H9 | J9: ='Entity TB (LCY)'!F9 | K9: 1.0089286 | L9: =J9*K9 | M9: ='Entity TB (LCY)'!G9 | N9: 11.91583 | O9: =M9*N9 | P9: ='Entity TB (LCY)'!H9 | Q9: 0.012111119 | R9: =P9*Q9 | S9: ='Entity TB (LCY)'!I9 | T9: 0.049243645 | U9: =S9*T9 | V9: ='Entity TB (LCY)'!J9 | W9: 4.6428307 | X9: =V9*W9 | Y9: ='Entity TB (LCY)'!K9 | Z9: 3.6725 | AA9: =Y9*Z9 | AB9: ='Entity TB (LCY)'!L9 | AC9: 1 | AD9: =AB9*AC9
A10: 5000 | B10: Doctor salaries | C10: Average | D10: ='Entity TB (LCY)'!D10 | E10: 1 | F10: =D10*E10 | G10: ='Entity TB (LCY)'!E10 | H10: 0.97933333 | I10: =G10*H10 | J10: ='Entity TB (LCY)'!F10 | K10: 1.0089286 | L10: =J10*K10 | M10: ='Entity TB (LCY)'!G10 | N10: 11.915734 | O10: =M10*N10 | P10: ='Entity TB (LCY)'!H10 | Q10: 0.012118684 | R10: =P10*Q10 | S10: ='Entity TB (LCY)'!I10 | T10: 0.049296916 | U10: =S10*T10 | V10: ='Entity TB (LCY)'!J10 | W10: 4.6487552 | X10: =V10*W10 | Y10: ='Entity TB (LCY)'!K10 | Z10: 3.6725 | AA10: =Y10*Z10 | AB10: ='Entity TB (LCY)'!L10 | AC10: 1 | AD10: =AB10*AC10
A11: 5100 | B11: Nursing & clinical staff | C11: Average | D11: ='Entity TB (LCY)'!D11 | E11: 1 | F11: =D11*E11 | G11: ='Entity TB (LCY)'!E11 | H11: 0.97933333 | I11: =G11*H11 | J11: ='Entity TB (LCY)'!F11 | K11: 1.0089286 | L11: =J11*K11 | M11: ='Entity TB (LCY)'!G11 | N11: 11.915742 | O11: =M11*N11 | P11: ='Entity TB (LCY)'!H11 | Q11: 0.012118238 | R11: =P11*Q11 | S11: ='Entity TB (LCY)'!I11 | T11: 0.049297642 | U11: =S11*T11 | V11: ='Entity TB (LCY)'!J11 | W11: 4.6483723 | X11: =V11*W11 | Y11: ='Entity TB (LCY)'!K11 | Z11: 3.6725 | AA11: =Y11*Z11 | AB11: ='Entity TB (LCY)'!L11 | AC11: 1 | AD11: =AB11*AC11
A12: 5200 | B12: Medical consumables | C12: Average | D12: ='Entity TB (LCY)'!D12 | E12: 1 | F12: =D12*E12 | G12: ='Entity TB (LCY)'!E12 | H12: 0.97933334 | I12: =G12*H12 | J12: ='Entity TB (LCY)'!F12 | K12: 1.0089286 | L12: =J12*K12 | M12: ='Entity TB (LCY)'!G12 | N12: 11.915977 | O12: =M12*N12 | P12: ='Entity TB (LCY)'!H12 | Q12: 0.012111694 | R12: =P12*Q12 | S12: ='Entity TB (LCY)'!I12 | T12: 0.049224268 | U12: =S12*T12 | V12: ='Entity TB (LCY)'!J12 | W12: 4.643122 | X12: =V12*W12 | Y12: ='Entity TB (LCY)'!K12 | Z12: 3.6725001 | AA12: =Y12*Z12 | AB12: ='Entity TB (LCY)'!L12 | AC12: 1 | AD12: =AB12*AC12
A13: 5300 | B13: Pharmacy cost of goods | C13: Average | D13: ='Entity TB (LCY)'!D13 | E13: 1 | F13: =D13*E13 | G13: ='Entity TB (LCY)'!E13 | H13: 0.97933334 | I13: =G13*H13 | J13: ='Entity TB (LCY)'!F13 | K13: 1.0089285 | L13: =J13*K13 | M13: ='Entity TB (LCY)'!G13 | N13: 11.915871 | O13: =M13*N13 | P13: ='Entity TB (LCY)'!H13 | Q13: 0.01210945 | R13: =P13*Q13 | S13: ='Entity TB (LCY)'!I13 | T13: 0.049279275 | U13: =S13*T13 | V13: ='Entity TB (LCY)'!J13 | W13: 4.6431844 | X13: =V13*W13 | Y13: ='Entity TB (LCY)'!K13 | Z13: 3.6725 | AA13: =Y13*Z13 | AB13: ='Entity TB (LCY)'!L13 | AC13: 1 | AD13: =AB13*AC13
A14: 6000 | B14: Rent & facility | C14: Average | D14: ='Entity TB (LCY)'!D14 | E14: 1 | F14: =D14*E14 | G14: ='Entity TB (LCY)'!E14 | H14: 0.97933333 | I14: =G14*H14 | J14: ='Entity TB (LCY)'!F14 | K14: 1.0089286 | L14: =J14*K14 | M14: ='Entity TB (LCY)'!G14 | N14: 11.915736 | O14: =M14*N14 | P14: ='Entity TB (LCY)'!H14 | Q14: 0.012118684 | R14: =P14*Q14 | S14: ='Entity TB (LCY)'!I14 | T14: 0.049296919 | U14: =S14*T14 | V14: ='Entity TB (LCY)'!J14 | W14: 4.6487553 | X14: =V14*W14 | Y14: ='Entity TB (LCY)'!K14 | Z14: 3.6724998 | AA14: =Y14*Z14 | AB14: ='Entity TB (LCY)'!L14 | AC14: 1 | AD14: =AB14*AC14
A15: 6100 | B15: Admin & front-office staff | C15: Average | D15: ='Entity TB (LCY)'!D15 | E15: 1 | F15: =D15*E15 | G15: ='Entity TB (LCY)'!E15 | H15: 0.97933329 | I15: =G15*H15 | J15: ='Entity TB (LCY)'!F15 | K15: 1.0089286 | L15: =J15*K15 | M15: ='Entity TB (LCY)'!G15 | N15: 11.915732 | O15: =M15*N15 | P15: ='Entity TB (LCY)'!H15 | Q15: 0.012118684 | R15: =P15*Q15 | S15: ='Entity TB (LCY)'!I15 | T15: 0.049296906 | U15: =S15*T15 | V15: ='Entity TB (LCY)'!J15 | W15: 4.6487552 | X15: =V15*W15 | Y15: ='Entity TB (LCY)'!K15 | Z15: 3.6724999 | AA15: =Y15*Z15 | AB15: ='Entity TB (LCY)'!L15 | AC15: 1 | AD15: =AB15*AC15
A16: 6200 | B16: Marketing | C16: Average | D16: ='Entity TB (LCY)'!D16 | E16: 1 | F16: =D16*E16 | G16: ='Entity TB (LCY)'!E16 | H16: 0.97933336 | I16: =G16*H16 | J16: ='Entity TB (LCY)'!F16 | K16: 1.0089286 | L16: =J16*K16 | M16: ='Entity TB (LCY)'!G16 | N16: 11.915944 | O16: =M16*N16 | P16: ='Entity TB (LCY)'!H16 | Q16: 0.012116774 | R16: =P16*Q16 | S16: ='Entity TB (LCY)'!I16 | T16: 0.049258097 | U16: =S16*T16 | V16: ='Entity TB (LCY)'!J16 | W16: 4.6657439 | X16: =V16*W16 | Y16: ='Entity TB (LCY)'!K16 | Z16: 3.6724999 | AA16: =Y16*Z16 | AB16: ='Entity TB (LCY)'!L16 | AC16: 1 | AD16: =AB16*AC16
... A27: 7200 | B27: Income tax | C27: Average | D27: ='Entity TB (LCY)'!D27 | E27: 1 | F27: =D27*E27 | G27: ='Entity TB (LCY)'!E27 | H27: 0.97933331 | I27: =G27*H27 | J27: ='Entity TB (LCY)'!F27 | K27: 1.0089288 | L27: =J27*K27 | M27: ='Entity TB (LCY)'!G27 | N27: 11.916581 | O27: =M27*N27 | P27: ='Entity TB (LCY)'!H27 | Q27: 0.012089104 | R27: =P27*Q27 | S27: ='Entity TB (LCY)'!I27 | T27: 0.048395928 | U27: =S27*T27 | V27: ='Entity TB (LCY)'!J27 | W27: 4.5983614 | X27: =V27*W27 | Y27: ='Entity TB (LCY)'!K27 | Z27: 3.6725022 | AA27: =Y27*Z27 | AB27: ='Entity TB (LCY)'!L27 | AC27: 1 | AD27: =AB27*AC27
A28: 1000 | B28: Cash & bank | C28: Closing | D28: ='Entity TB (LCY)'!D28 | E28: 1 | F28: =D28*E28 | G28: ='Entity TB (LCY)'!E28 | H28: ='FX Rates'!I26 | I28: =G28*H28 | J28: ='Entity TB (LCY)'!F28 | K28: ='FX Rates'!J26 | L28: =J28*K28 | M28: ='Entity TB (LCY)'!G28 | N28: ='FX Rates'!K26 | O28: =M28*N28 | P28: ='Entity TB (LCY)'!H28 | Q28: ='FX Rates'!L26 | R28: =P28*Q28 | S28: ='Entity TB (LCY)'!I28 | T28: ='FX Rates'!M26 | U28: =S28*T28 | V28: ='Entity TB (LCY)'!J28 | W28: ='FX Rates'!N26 | X28: =V28*W28 | Y28: ='Entity TB (LCY)'!K28 | Z28: ='FX Rates'!O26 | AA28: =Y28*Z28 | AB28: ='Entity TB (LCY)'!L28 | AC28: 1 | AD28: =AB28*AC28
A29: 1100 | B29: Insurance receivables | C29: Closing | D29: ='Entity TB (LCY)'!D29 | E29: 1 | F29: =D29*E29 | G29: ='Entity TB (LCY)'!E29 | H29: ='FX Rates'!I26 | I29: =G29*H29 | J29: ='Entity TB (LCY)'!F29 | K29: ='FX Rates'!J26 | L29: =J29*K29 | M29: ='Entity TB (LCY)'!G29 | N29: ='FX Rates'!K26 | O29: =M29*N29 | P29: ='Entity TB (LCY)'!H29 | Q29: ='FX Rates'!L26 | R29: =P29*Q29 | S29: ='Entity TB (LCY)'!I29 | T29: ='FX Rates'!M26 | U29: =S29*T29 | V29: ='Entity TB (LCY)'!J29 | W29: ='FX Rates'!N26 | X29: =V29*W29 | Y29: ='Entity TB (LCY)'!K29 | Z29: ='FX Rates'!O26 | AA29: =Y29*Z29 | AB29: ='Entity TB (LCY)'!L29 | AC29: 1 | AD29: =AB29*AC29
A30: 1200 | B30: Inventory (medical & pharmacy) | C30: Closing | D30: ='Entity TB (LCY)'!D30 | E30: 1 | F30: =D30*E30 | G30: ='Entity TB (LCY)'!E30 | H30: ='FX Rates'!I26 | I30: =G30*H30 | J30: ='Entity TB (LCY)'!F30 | K30: ='FX Rates'!J26 | L30: =J30*K30 | M30: ='Entity TB (LCY)'!G30 | N30: ='FX Rates'!K26 | O30: =M30*N30 | P30: ='Entity TB (LCY)'!H30 | Q30: ='FX Rates'!L26 | R30: =P30*Q30 | S30: ='Entity TB (LCY)'!I30 | T30: ='FX Rates'!M26 | U30: =S30*T30 | V30: ='Entity TB (LCY)'!J30 | W30: ='FX Rates'!N26 | X30: =V30*W30 | Y30: ='Entity TB (LCY)'!K30 | Z30: ='FX Rates'!O26 | AA30: =Y30*Z30 | AB30: ='Entity TB (LCY)'!L30 | AC30: 1 | AD30: =AB30*AC30
A31: 1300 | B31: Prepayments & deposits | C31: Closing | D31: ='Entity TB (LCY)'!D31 | E31: 1 | F31: =D31*E31 | G31: ='Entity TB (LCY)'!E31 | H31: ='FX Rates'!I26 | I31: =G31*H31 | J31: ='Entity TB (LCY)'!F31 | K31: ='FX Rates'!J26 | L31: =J31*K31 | M31: ='Entity TB (LCY)'!G31 | N31: ='FX Rates'!K26 | O31: =M31*N31 | P31: ='Entity TB (LCY)'!H31 | Q31: ='FX Rates'!L26 | R31: =P31*Q31 | S31: ='Entity TB (LCY)'!I31 | T31: ='FX Rates'!M26 | U31: =S31*T31 | V31: ='Entity TB (LCY)'!J31 | W31: ='FX Rates'!N26 | X31: =V31*W31 | Y31: ='Entity TB (LCY)'!K31 | Z31: ='FX Rates'!O26 | AA31: =Y31*Z31 | AB31: ='Entity TB (LCY)'!L31 | AC31: 1 | AD31: =AB31*AC31
A32: 1400 | B32: Property, plant & equipment | C32: Closing | D32: ='Entity TB (LCY)'!D32 | E32: 1 | F32: =D32*E32 | G32: ='Entity TB (LCY)'!E32 | H32: ='FX Rates'!I26 | I32: =G32*H32 | J32: ='Entity TB (LCY)'!F32 | K32: ='FX Rates'!J26 | L32: =J32*K32 | M32: ='Entity TB (LCY)'!G32 | N32: ='FX Rates'!K26 | O32: =M32*N32 | P32: ='Entity TB (LCY)'!H32 | Q32: ='FX Rates'!L26 | R32: =P32*Q32 | S32: ='Entity TB (LCY)'!I32 | T32: ='FX Rates'!M26 | U32: =S32*T32 | V32: ='Entity TB (LCY)'!J32 | W32: ='FX Rates'!N26 | X32: =V32*W32 | Y32: ='Entity TB (LCY)'!K32 | Z32: ='FX Rates'!O26 | AA32: =Y32*Z32 | AB32: ='Entity TB (LCY)'!L32 | AC32: 1 | AD32: =AB32*AC32
A33: 1500 | B33: Investment in subsidiaries | C33: Historical | D33: ='Entity TB (LCY)'!D33 | E33: 1 | F33: =D33*E33 | G33: ='Entity TB (LCY)'!E33 | H33: 1 | I33: =G33*H33 | J33: ='Entity TB (LCY)'!F33 | K33: 1 | L33: =J33*K33 | M33: ='Entity TB (LCY)'!G33 | N33: 1 | O33: =M33*N33 | P33: ='Entity TB (LCY)'!H33 | Q33: 1 | R33: =P33*Q33 | S33: ='Entity TB (LCY)'!I33 | T33: 1 | U33: =S33*T33 | V33: ='Entity TB (LCY)'!J33 | W33: 1 | X33: =V33*W33 | Y33: ='Entity TB (LCY)'!K33 | Z33: 1 | AA33: =Y33*Z33 | AB33: ='Entity TB (LCY)'!L33 | AC33: 1 | AD33: =AB33*AC33
A34: 2000 | B34: Trade payables | C34: Closing | D34: ='Entity TB (LCY)'!D34 | E34: 1 | F34: =D34*E34 | G34: ='Entity TB (LCY)'!E34 | H34: ='FX Rates'!I26 | I34: =G34*H34 | J34: ='Entity TB (LCY)'!F34 | K34: ='FX Rates'!J26 | L34: =J34*K34 | M34: ='Entity TB (LCY)'!G34 | N34: ='FX Rates'!K26 | O34: =M34*N34 | P34: ='Entity TB (LCY)'!H34 | Q34: ='FX Rates'!L26 | R34: =P34*Q34 | S34: ='Entity TB (LCY)'!I34 | T34: ='FX Rates'!M26 | U34: =S34*T34 | V34: ='Entity TB (LCY)'!J34 | W34: ='FX Rates'!N26 | X34: =V34*W34 | Y34: ='Entity TB (LCY)'!K34 | Z34: ='FX Rates'!O26 | AA34: =Y34*Z34 | AB34: ='Entity TB (LCY)'!L34 | AC34: 1 | AD34: =AB34*AC34
A35: 2100 | B35: Accrued salaries & benefits | C35: Closing | D35: ='Entity TB (LCY)'!D35 | E35: 1 | F35: =D35*E35 | G35: ='Entity TB (LCY)'!E35 | H35: ='FX Rates'!I26 | I35: =G35*H35 | J35: ='Entity TB (LCY)'!F35 | K35: ='FX Rates'!J26 | L35: =J35*K35 | M35: ='Entity TB (LCY)'!G35 | N35: ='FX Rates'!K26 | O35: =M35*N35 | P35: ='Entity TB (LCY)'!H35 | Q35: ='FX Rates'!L26 | R35: =P35*Q35 | S35: ='Entity TB (LCY)'!I35 | T35: ='FX Rates'!M26 | U35: =S35*T35 | V35: ='Entity TB (LCY)'!J35 | W35: ='FX Rates'!N26 | X35: =V35*W35 | Y35: ='Entity TB (LCY)'!K35 | Z35: ='FX Rates'!O26 | AA35: =Y35*Z35 | AB35: ='Entity TB (LCY)'!L35 | AC35: 1 | AD35: =AB35*AC35
A36: 2200 | B36: Income tax payable | C36: Closing | D36: ='Entity TB (LCY)'!D36 | E36: 1 | F36: =D36*E36 | G36: ='Entity TB (LCY)'!E36 | H36: ='FX Rates'!I26 | I36: =G36*H36 | J36: ='Entity TB (LCY)'!F36 | K36: ='FX Rates'!J26 | L36: =J36*K36 | M36: ='Entity TB (LCY)'!G36 | N36: ='FX Rates'!K26 | O36: =M36*N36 | P36: ='Entity TB (LCY)'!H36 | Q36: ='FX Rates'!L26 | R36: =P36*Q36 | S36: ='Entity TB (LCY)'!I36 | T36: ='FX Rates'!M26 | U36: =S36*T36 | V36: ='Entity TB (LCY)'!J36 | W36: ='FX Rates'!N26 | X36: =V36*W36 | Y36: ='Entity TB (LCY)'!K36 | Z36: ='FX Rates'!O26 | AA36: =Y36*Z36 | AB36: ='Entity TB (LCY)'!L36 | AC36: 1 | AD36: =AB36*AC36
A37: 2300 | B37: Bank borrowings | C37: Closing | D37: ='Entity TB (LCY)'!D37 | E37: 1 | F37: =D37*E37 | G37: ='Entity TB (LCY)'!E37 | H37: ='FX Rates'!I26 | I37: =G37*H37 | J37: ='Entity TB (LCY)'!F37 | K37: ='FX Rates'!J26 | L37: =J37*K37 | M37: ='Entity TB (LCY)'!G37 | N37: ='FX Rates'!K26 | O37: =M37*N37 | P37: ='Entity TB (LCY)'!H37 | Q37: ='FX Rates'!L26 | R37: =P37*Q37 | S37: ='Entity TB (LCY)'!I37 | T37: ='FX Rates'!M26 | U37: =S37*T37 | V37: ='Entity TB (LCY)'!J37 | W37: ='FX Rates'!N26 | X37: =V37*W37 | Y37: ='Entity TB (LCY)'!K37 | Z37: ='FX Rates'!O26 | AA37: =Y37*Z37 | AB37: ='Entity TB (LCY)'!L37 | AC37: 1 | AD37: =AB37*AC37
A38: 3000 | B38: Share capital | C38: Historical | D38: ='Entity TB (LCY)'!D38 | E38: 1 | F38: =D38*E38 | G38: ='Entity TB (LCY)'!E38 | H38: 0.97933333 | I38: =G38*H38 | J38: ='Entity TB (LCY)'!F38 | K38: 1.0089286 | L38: =J38*K38 | M38: ='Entity TB (LCY)'!G38 | N38: 12.08 | O38: =M38*N38 | P38: ='Entity TB (LCY)'!H38 | Q38: 0.030102459 | R38: =P38*Q38 | S38: ='Entity TB (LCY)'!I38 | T38: 0.041732955 | U38: =S38*T38 | V38: ='Entity TB (LCY)'!J38 | W38: 4.85 | X38: =V38*W38 | Y38: ='Entity TB (LCY)'!K38 | Z38: 3.6725 | AA38: =Y38*Z38 | AB38: ='Entity TB (LCY)'!L38 | AC38: 1 | AD38: =AB38*AC38
A39: 3100 | B39: Retained earnings | C39: Historical (P&L at average rates) | D39: ='Entity TB (LCY)'!D39 | E39: roll-fwd | F39: 30125158 | G39: ='Entity TB (LCY)'!E39 | H39: roll-fwd | I39: 18147174 | J39: ='Entity TB (LCY)'!F39 | K39: roll-fwd | L39: 9691400 | M39: ='Entity TB (LCY)'!G39 | N39: roll-fwd | O39: 15330102 | P39: ='Entity TB (LCY)'!H39 | Q39: roll-fwd | R39: -1834246 | S39: ='Entity TB (LCY)'!I39 | T39: roll-fwd | U39: 446772 | V39: ='Entity TB (LCY)'!J39 | W39: roll-fwd | X39: -3366046 | Y39: ='Entity TB (LCY)'!K39 | Z39: roll-fwd | AA39: -5916659 | AB39: ='Entity TB (LCY)'!L39 | AC39: roll-fwd | AD39: -6815079
A40: 3200 | B40: Translation reserve (CTA) | C40: Balancing figure | F40: =(F28+F29+F30+F31+F32+F33)-(F34+F35+F36+F37)-F38-F39 | I40: =(I28+I29+I30+I31+I32+I33)-(I34+I35+I36+I37)-I38-I39 | L40: =(L28+L29+L30+L31+L32+L33)-(L34+L35+L36+L37)-L38-L39 | O40: =(O28+O29+O30+O31+O32+O33)-(O34+O35+O36+O37)-O38-O39 | R40: =(R28+R29+R30+R31+R32+R33)-(R34+R35+R36+R37)-R38-R39 | U40: =(U28+U29+U30+U31+U32+U33)-(U34+U35+U36+U37)-U38-U39 | X40: =(X28+X29+X30+X31+X32+X33)-(X34+X35+X36+X37)-X38-X39 | AA40: =(AA28+AA29+AA30+AA31+AA32+AA33)-(AA34+AA35+AA36+AA37)-AA38-AA39 | AD40: =(AD28+AD29+AD30+AD31+AD32+AD33)-(AD34+AD35+AD36+AD37)-AD38-AD39
B42: Check: CTA per Power BI data | F42: 0 | I42: 0 | L42: 0 | O42: -335934 | R42: -5259465 | U42: -2905 | X42: -935230 | AA42: 0 | AD42: 0

Sheet Eliminations
A1: Consolidation eliminations - Jan-Sep 2026 and 30 September 2026
A2: Intercompany items cancel out so the group is shown as one company.
A4: # | B4: Elimination | C4: Account | D4: Debit / (credit) AED | E4: Explanation
A5: 1 | B5: Management fee | C5: 4800 Management fee income (holding) | D5: -12018850 | E5: Remove the holding company's fee income
A6: 1 | B6: Management fee | C6: 6500 Management fee expense (subsidiaries) | D6: 12018850 | E6: Remove the subsidiaries' fee expense - net effect on group profit nil
A7: 2 | B7: Investment in subsidiaries | C7: 3000 Share capital (subsidiaries, historical rate) | D7: -1.3172198e+08 | E7: Subsidiaries' share capital at the rate when it was injected
A8: 2 | B8: Investment in subsidiaries | C8: 1500 Investment in subsidiaries (holding) | D8: 1.3172198e+08 | E8: Holding company's cost of investment - equal by construction

Sheet Consolidation
A1: Consolidation worksheet - AED
A2: Jan-Sep 2026 P&L and 30-Sep-2026 balance sheet. Each entity column links to the Translation sheet; Consolidated = entities + eliminations.
A4: Account | B4: Name | C4: UAE | D4: KSA | E4: Qatar | F4: Kuwait | G4: Pakistan | H4: Afghanistan | I4: UK | J4: USA | K4: Head office | L4: Eliminations | M4: Consolidated
A5: 4000 | B5: Consultation revenue | C5: =Translation!F5 | D5: =Translation!I5 | E5: =Translation!L5 | F5: =Translation!O5 | G5: =Translation!R5 | H5: =Translation!U5 | I5: =Translation!X5 | J5: =Translation!AA5 | K5: =Translation!AD5 | L5: 0 | M5: =SUM(C5:L5)
A6: 4100 | B6: Procedures revenue | C6: =Translation!F6 | D6: =Translation!I6 | E6: =Translation!L6 | F6: =Translation!O6 | G6: =Translation!R6 | H6: =Translation!U6 | I6: =Translation!X6 | J6: =Translation!AA6 | K6: =Translation!AD6 | L6: 0 | M6: =SUM(C6:L6)
A7: 4200 | B7: Diagnostics revenue | C7: =Translation!F7 | D7: =Translation!I7 | E7: =Translation!L7 | F7: =Translation!O7 | G7: =Translation!R7 | H7: =Translation!U7 | I7: =Translation!X7 | J7: =Translation!AA7 | K7: =Translation!AD7 | L7: 0 | M7: =SUM(C7:L7)
A8: 4300 | B8: Pharmacy revenue | C8: =Translation!F8 | D8: =Translation!I8 | E8: =Translation!L8 | F8: =Translation!O8 | G8: =Translation!R8 | H8: =Translation!U8 | I8: =Translation!X8 | J8: =Translation!AA8 | K8: =Translation!AD8 | L8: 0 | M8: =SUM(C8:L8)
A9: 4900 | B9: Contractual discounts | C9: =Translation!F9 | D9: =Translation!I9 | E9: =Translation!L9 | F9: =Translation!O9 | G9: =Translation!R9 | H9: =Translation!U9 | I9: =Translation!X9 | J9: =Translation!AA9 | K9: =Translation!AD9 | L9: 0 | M9: =SUM(C9:L9)
A10: 5000 | B10: Doctor salaries | C10: =Translation!F10 | D10: =Translation!I10 | E10: =Translation!L10 | F10: =Translation!O10 | G10: =Translation!R10 | H10: =Translation!U10 | I10: =Translation!X10 | J10: =Translation!AA10 | K10: =Translation!AD10 | L10: 0 | M10: =SUM(C10:L10)
A11: 5100 | B11: Nursing & clinical staff | C11: =Translation!F11 | D11: =Translation!I11 | E11: =Translation!L11 | F11: =Translation!O11 | G11: =Translation!R11 | H11: =Translation!U11 | I11: =Translation!X11 | J11: =Translation!AA11 | K11: =Translation!AD11 | L11: 0 | M11: =SUM(C11:L11)
A12: 5200 | B12: Medical consumables | C12: =Translation!F12 | D12: =Translation!I12 | E12: =Translation!L12 | F12: =Translation!O12 | G12: =Translation!R12 | H12: =Translation!U12 | I12: =Translation!X12 | J12: =Translation!AA12 | K12: =Translation!AD12 | L12: 0 | M12: =SUM(C12:L12)
A13: 5300 | B13: Pharmacy cost of goods | C13: =Translation!F13 | D13: =Translation!I13 | E13: =Translation!L13 | F13: =Translation!O13 | G13: =Translation!R13 | H13: =Translation!U13 | I13: =Translation!X13 | J13: =Translation!AA13 | K13: =Translation!AD13 | L13: 0 | M13: =SUM(C13:L13)
A14: 6000 | B14: Rent & facility | C14: =Translation!F14 | D14: =Translation!I14 | E14: =Translation!L14 | F14: =Translation!O14 | G14: =Translation!R14 | H14: =Translation!U14 | I14: =Translation!X14 | J14: =Translation!AA14 | K14: =Translation!AD14 | L14: 0 | M14: =SUM(C14:L14)
A15: 6100 | B15: Admin & front-office staff | C15: =Translation!F15 | D15: =Translation!I15 | E15: =Translation!L15 | F15: =Translation!O15 | G15: =Translation!R15 | H15: =Translation!U15 | I15: =Translation!X15 | J15: =Translation!AA15 | K15: =Translation!AD15 | L15: 0 | M15: =SUM(C15:L15)
A16: 6200 | B16: Marketing | C16: =Translation!F16 | D16: =Translation!I16 | E16: =Translation!L16 | F16: =Translation!O16 | G16: =Translation!R16 | H16: =Translation!U16 | I16: =Translation!X16 | J16: =Translation!AA16 | K16: =Translation!AD16 | L16: 0 | M16: =SUM(C16:L16)
... A40: 3200 | B40: Translation reserve (CTA) | C40: =Translation!F40 | D40: =Translation!I40 | E40: =Translation!L40 | F40: =Translation!O40 | G40: =Translation!R40 | H40: =Translation!U40 | I40: =Translation!X40 | J40: =Translation!AA40 | K40: =Translation!AD40 | L40: 0 | M40: =SUM(C40:L40)
B42: Net profit (P&L total) | M42: =SUM(M5,M6,M7,M8,M9,M10,M11,M12,M13,M14,M15,M16,M17,M18,M19,M20,M21,M22,M23,M24,M25,M26,M27)
B43: Total assets | M43: =M28+M29+M30+M31+M32+M33
B44: Total liabilities + equity | M44: =M34+M35+M36+M37+M38+M39+M40
B45: Balance check (must be 0) | M45: =M43-M44

Sheet Consolidated P&L
A1: Ravaan Medical Group - consolidated income statement (AED)
A2: Actual vs budget and prior year. Budget translated at budget rates; actuals at monthly average rates.
A4: Line | B4: FY2025 | C4: YTD Sep-25 | D4: YTD Sep-26 | E4: Budget YTD Sep-26 | F4: Var vs budget | G4: Var vs PY | H4: Var vs PY %
A5: Consultation revenue | B5: 199074897 | C5: 146189497 | D5: 164098431 | E5: 173586055 | F5: =D5-E5 | G5: =D5-C5 | H5: =IF(C5=0,"",(D5-C5)/ABS(C5))
A6: Procedures revenue | B6: 153426525 | C6: 112811826 | D6: 130437490 | E6: 135195872 | F6: =D6-E6 | G6: =D6-C6 | H6: =IF(C6=0,"",(D6-C6)/ABS(C6))
A7: Diagnostics revenue | B7: 41293877 | C7: 30306087 | D7: 34528629 | E7: 36658464 | F7: =D7-E7 | G7: =D7-C7 | H7: =IF(C7=0,"",(D7-C7)/ABS(C7))
A8: Pharmacy revenue | B8: 39486723 | C8: 29002807 | D8: 32759975 | E8: 34634022 | F8: =D8-E8 | G8: =D8-C8 | H8: =IF(C8=0,"",(D8-C8)/ABS(C8))
A9: Gross revenue | B9: 433282022 | C9: 318310216 | D9: 361824526 | E9: 380074413 | F9: =D9-E9 | G9: =D9-C9 | H9: =IF(C9=0,"",(D9-C9)/ABS(C9))
A10: Contractual discounts | B10: -75435679 | C10: -55615569 | D10: -61353278 | E10: -64875205 | F10: =D10-E10 | G10: =D10-C10 | H10: =IF(C10=0,"",(D10-C10)/ABS(C10))
A11: Net revenue | B11: 357846343 | C11: 262694647 | D11: 300471248 | E11: 315199207 | F11: =D11-E11 | G11: =D11-C11 | H11: =IF(C11=0,"",(D11-C11)/ABS(C11))
A12: Doctor salaries | B12: -117377423 | C12: -87340721 | D12: -98981586 | E12: -100121513 | F12: =D12-E12 | G12: =D12-C12 | H12: =IF(C12=0,"",(D12-C12)/ABS(C12))
A13: Nursing & clinical staff | B13: -33917294 | C13: -25251843 | D13: -28526340 | E13: -28819628 | F13: =D13-E13 | G13: =D13-C13 | H13: =IF(C13=0,"",(D13-C13)/ABS(C13))
A14: Medical consumables | B14: -28415958 | C14: -20866973 | D14: -24186133 | E14: -25221167 | F14: =D14-E14 | G14: =D14-C14 | H14: =IF(C14=0,"",(D14-C14)/ABS(C14))
A15: Pharmacy cost of goods | B15: -22163986 | C15: -16263479 | D15: -18425175 | E15: -19511952 | F15: =D15-E15 | G15: =D15-C15 | H15: =IF(C15=0,"",(D15-C15)/ABS(C15))
A16: Gross profit | B16: 155971683 | C16: 112971631 | D16: 130352014 | E16: 141524948 | F16: =D16-E16 | G16: =D16-C16 | H16: =IF(C16=0,"",(D16-C16)/ABS(C16))
... A32: Net profit | B32: 12857867 | C32: 7004807 | D32: 15555327 | E32: 24394361 | F32: =D32-E32 | G32: =D32-C32 | H32: =IF(C32=0,"",(D32-C32)/ABS(C32))
A34: Gross margin % | B34: =B16/B11 | C34: =C16/C11 | D34: =D16/D11 | E34: =E16/E11
A35: EBITDA margin % | B35: =B26/B11 | C35: =C26/C11 | D35: =D26/D11 | E35: =E26/E11
A36: Net margin % | B36: =B32/B11 | C36: =C32/C11 | D36: =D32/D11 | E36: =E32/E11

Sheet Consolidated BS
A1: Ravaan Medical Group - consolidated balance sheet (AED)
A2: Closing rates at each date; equity at historical rates; translation reserve balances.
A4: Line | B4: 31-Dec-2024 | C4: 31-Dec-2025 | D4: 30-Sep-2026
A5: Cash & bank | B5: 55861694 | C5: 80327815 | D5: 97948948
A6: Insurance receivables | B6: 52474532 | C6: 57221183 | D6: 60452182
A7: Inventory (medical & pharmacy) | B7: 5795036 | C7: 6353011 | D7: 7531149
A8: Prepayments & deposits | B8: 2457639 | C8: 2746737 | D8: 2775568
A9: Property, plant & equipment | B9: 107066517 | C9: 100130174 | D9: 84203822
A10: Total assets | B10: 223655419 | C10: 246778919 | D10: 252911669
A11: Trade payables | B11: 7536674 | C11: 8476332 | D11: 9587304
A12: Accrued salaries & benefits | B12: 7687358 | C12: 8547355 | D12: 8824578
A13: Income tax payable | B13: 1315963 | C13: 1773727 | D13: 1441444
A14: Bank borrowings | B14: 38041667 | C14: 45925726 | D14: 37061320
A15: Total liabilities | B15: 54581661 | C15: 64723139 | D15: 56914645
A16: Share capital | B16: 146721982 | C16: 146721982 | D16: 146721982
... A20: Total liabilities & equity | B20: 223655419 | C20: 246778919 | D20: 252911669
A21: Check: assets - liabilities - equity | B21: =B10-B20 | C21: =C10-C20 | D21: =D10-D20

Sheet Consolidated CF
A1: Ravaan Medical Group - consolidated cash flow (AED, indirect)
A2: Each entity's local-currency cash flows translated at monthly average rates; the difference to the change in translated cash is the effect of exchange rates.
A4: Line | B4: FY2025 | C4: YTD Sep-26
A5: Net profit | B5: 12857867 | C5: 15555327
A6: Depreciation & amortisation | B6: 23016804 | C6: 17282407
A7: Change in insurance receivables | B7: -4483388 | C7: -3872902
A8: Change in inventory | B8: -505640 | C8: -1317078
A9: Change in prepayments | B9: -265753 | C9: -92467
A10: Change in trade payables | B10: 877217 | C10: 1292940
A11: Change in accrued salaries | B11: 812499 | C11: 433834
A12: Change in tax payable | B12: 430023 | C12: -297793
A13: Cash from operating activities | B13: 32739629 | C13: 28984266
A14: Capital expenditure | B14: -15929186 | C14: -3305184
A15: Cash used in investing | B15: -15929186 | C15: -3305184
A16: Net borrowings / (repayments) | B16: 7435645 | C16: -6727490
... A21: Closing cash | B21: 80327815 | C21: 97948948
A22: Check: opening + change - closing | B22: =B20+B19-B21 | C22: =C20+C19-C21

Sheet CTA Roll-forward
A1: Translation reserve (CTA) by entity - AED
A2: Negative = the local currency weakened against the AED while the group held net assets there.
A4: Entity | B4: Currency | C4: CTA 31-Dec-24 | D4: Movement FY2025 | E4: CTA 31-Dec-25 | F4: Movement Jan-Sep 26 | G4: CTA 30-Sep-26
A5: UAE - Ravaan Medical Centres LLC | B5: AED | C5: 0 | D5: 0 | E5: 0 | F5: 0 | G5: 0
A6: KSA - Ravaan Medical Company | B6: SAR | C6: 0 | D6: 0 | E6: 0 | F6: 0 | G6: 0
A7: Qatar - Ravaan Healthcare WLL | B7: QAR | C7: 0 | D7: 0 | E7: 0 | F7: 0 | G7: 0
A8: Kuwait - Ravaan Clinics Company KSCC | B8: KWD | C8: -224941 | D8: -24096 | E8: -249037 | F8: -86897 | G8: -335934
A9: Pakistan - Ravaan Health (Private) Limited | B9: PKR | C9: -4676723 | D9: -32103 | E9: -4708826 | F9: -550639 | G9: -5259465
A10: Afghanistan - Ravaan Medical Services | B10: AFN | C10: 257208 | D10: 20485 | E10: 277694 | F10: -280599 | G10: -2905
A11: UK - Ravaan Clinics UK Limited | B11: GBP | C11: -399151 | D11: 159869 | E11: -239282 | F11: -695948 | G11: -935230
A12: USA - Ravaan Medical Group USA Inc. | B12: USD | C12: 0 | D12: 0 | E12: 0 | F12: 0 | G12: 0
A13: Head office - Ravaan Medical Group Holding Ltd | B13: AED | C13: 0 | D13: 0 | E13: 0 | F13: 0 | G13: 0
A14: Group | C14: =SUM(C5:C13) | D14: =SUM(D5:D13) | E14: =SUM(E5:E13) | F14: =SUM(F5:F13) | G14: =SUM(G5:G13)

Sheet Constant Currency
A1: Net revenue and EBITDA growth - reported vs constant currency (Jan-Sep 2026 vs Jan-Sep 2025)
A2: Constant currency = 2026 local-currency results translated at 2025 average rates.
A4: Country | B4: Currency | C4: Revenue LCY 2026 | D4: Revenue LCY 2025 | E4: LCY growth % | F4: Revenue AED 2026 (reported) | G4: Revenue AED 2026 at 2025 rates | H4: Revenue AED 2025 | I4: Organic growth AED | J4: FX impact AED | K4: Reported growth % | L4: Constant-currency growth %
A5: UAE | B5: AED | C5: 77408630 | D5: 70095718 | E5: =IF(D5=0,"",C5/D5-1) | F5: 77408630 | G5: 77408630 | H5: 70095718 | I5: =G5-H5 | J5: =F5-G5 | K5: =IF(H5=0,"",F5/H5-1) | L5: =IF(H5=0,"",G5/H5-1)
A6: KSA | B6: SAR | C6: 52614526 | D6: 44691275 | E6: =IF(D6=0,"",C6/D6-1) | F6: 51527159 | G6: 51527159 | H6: 43767656 | I6: =G6-H6 | J6: =F6-G6 | K6: =IF(H6=0,"",F6/H6-1) | L6: =IF(H6=0,"",G6/H6-1)
A7: Qatar | B7: QAR | C7: 27505224 | D7: 26002277 | E7: =IF(D7=0,"",C7/D7-1) | F7: 27750806 | G7: 27750806 | H7: 26234440 | I7: =G7-H7 | J7: =F7-G7 | K7: =IF(H7=0,"",F7/H7-1) | L7: =IF(H7=0,"",G7/H7-1)
A8: Kuwait | B8: KWD | C8: 2558183 | D8: 2384209 | E8: =IF(D8=0,"",C8/D8-1) | F8: 30482879 | G8: 30519240 | H8: 28443737 | I8: =G8-H8 | J8: =F8-G8 | K8: =IF(H8=0,"",F8/H8-1) | L8: =IF(H8=0,"",G8/H8-1)
A9: Pakistan | B9: PKR | C9: 566089142 | D9: 441806721 | E9: =IF(D9=0,"",C9/D9-1) | F9: 6855951 | G9: 7404328 | H9: 5778830 | I9: =G9-H9 | J9: =F9-G9 | K9: =IF(H9=0,"",F9/H9-1) | L9: =IF(H9=0,"",G9/H9-1)
A10: Afghanistan | B10: AFN | C10: 22382888 | D10: 20149407 | E10: =IF(D10=0,"",C10/D10-1) | F10: 1102198 | G10: 1183423 | H10: 1065290 | I10: =G10-H10 | J10: =F10-G10 | K10: =IF(H10=0,"",F10/H10-1) | L10: =IF(H10=0,"",G10/H10-1)
A11: UK | B11: GBP | C11: 10551698 | D11: 6769681 | E11: =IF(D11=0,"",C11/D11-1) | F11: 48989350 | G11: 51345535 | H11: 32892344 | I11: =G11-H11 | J11: =F11-G11 | K11: =IF(H11=0,"",F11/H11-1) | L11: =IF(H11=0,"",G11/H11-1)
A12: USA | B12: USD | C12: 15344935 | D12: 14817327 | E12: =IF(D12=0,"",C12/D12-1) | F12: 56354273 | G12: 56354273 | H12: 54416632 | I12: =G12-H12 | J12: =F12-G12 | K12: =IF(H12=0,"",F12/H12-1) | L12: =IF(H12=0,"",G12/H12-1)
A13: Group | F13: =SUM(F5:F12) | G13: =SUM(G5:G12) | H13: =SUM(H5:H12) | I13: =SUM(I5:I12) | J13: =SUM(J5:J12) | K13: =F13/H13-1 | L13: =G13/H13-1
